xv/__init__.py
xv/data_access.py
xv/util.py
xv-0.1.3.dist-info/LICENSE
xv-0.1.3.dist-info/METADATA
xv-0.1.3.dist-info/WHEEL
xv-0.1.3.dist-info/top_level.txt
xv-0.1.3.dist-info/RECORD
