Metadata-Version: 2.1
Name: xv
Version: 0.1.3
Summary: Access to arxiv data
Home-page: https://github.com/thorwhalen/xv
Author: Thor Whalen
License: mit
Platform: any
License-File: LICENSE
Requires-Dist: dol
Requires-Dist: config2py
Requires-Dist: graze
Requires-Dist: pandas
Requires-Dist: pyarrow
